LICENSE
README.md
setup.py
qmathlib/__init__.py
qmathlib/quickmath.py
qmathlib.egg-info/PKG-INFO
qmathlib.egg-info/SOURCES.txt
qmathlib.egg-info/dependency_links.txt
qmathlib.egg-info/top_level.txt